yoneda/__init__.py
yoneda/basic.py
yoneda/monad.py
yoneda/py.typed
yoneda-0.2.0.dist-info/WHEEL
yoneda-0.2.0.dist-info/METADATA
yoneda-0.2.0.dist-info/licenses/LICENSE
yoneda-0.2.0.dist-info/RECORD
