Metadata-Version: 2.1
Name: yoneda
Version: 0.2.0
Summary: Category theory in python.
License: MIT
Keywords: category,category-theory,monad,monoid,functor,isomorphism,morphism,arrow
Author-email: Alex Braun <alexander.g.braun@gmail.com>
Requires-Python: >=3.10
Classifier: Development Status :: 4 - Beta
Classifier: Intended Audience :: Developers
Classifier: License :: OSI Approved :: MIT License
Classifier: Programming Language :: Python :: 3
Classifier: Programming Language :: Python :: 3.10
Classifier: Programming Language :: Python :: 3.11
Classifier: Programming Language :: Python :: 3.12
Classifier: Programming Language :: Python :: 3.13
Classifier: Typing :: Typed
Requires-Dist: infix>=1.2
Requires-Dist: lunchbox
Project-URL: documentation, https://theNewFlesh.github.io/yoneda
Project-URL: repository, https://github.com/theNewFlesh/yoneda
